dogsled/__init__.py
dogsled/__main__.py
dogsled/config.py
dogsled/defaults.py
dogsled/errors.py
dogsled/libvips_downloader.py
dogsled/normaliser.py
dogsled/paths.py
dogsled/resources.py
dogsled/slides.py
dogsled/user_input.py
dogsled-0.0.5.dist-info/LICENSE
dogsled-0.0.5.dist-info/METADATA
dogsled-0.0.5.dist-info/WHEEL
dogsled-0.0.5.dist-info/top_level.txt
dogsled-0.0.5.dist-info/RECORD
