Metadata-Version: 2.1
Name: dogsled
Version: 0.0.5
Summary: Macenko medical slide normalisation
Home-page: https://github.com/RhDm/dogsled
Author: Dmitri Stepanov
Author-email: dmitri.stepanov1@gmail.com
License: UNKNOWN
Project-URL: Bug Tracker, https://github.com/RhDm/dogsled/issues
Platform: UNKNOWN
Classifier: Development Status :: 3 - Alpha
Classifier: Programming Language :: Python :: 3
Classifier: License :: OSI Approved :: GNU General Public License v3 (GPLv3)
Classifier: Operating System :: MacOS
Classifier: Operating System :: Unix
Classifier: Operating System :: Microsoft :: Windows
Requires-Python: >=3.8
License-File: LICENSE
Requires-Dist: paquo (>=0.4.0)
Requires-Dist: dynaconf (>=3.1.7)
Requires-Dist: numpy (>=1.21.4)
Requires-Dist: psutil (>=5.8.0)
Requires-Dist: pyvips (>=2.1.16)
Requires-Dist: scipy (>=1.7.3)
Requires-Dist: numba
Provides-Extra: dev
Requires-Dist: pytest (>=6) ; extra == 'dev'
Requires-Dist: pytest-cov ; extra == 'dev'
Requires-Dist: line-profiler (>=3.3.1) ; extra == 'dev'
Requires-Dist: memory-profiler (>=0.58.0) ; extra == 'dev'
Provides-Extra: docs
Requires-Dist: sphinx ; extra == 'docs'
Requires-Dist: pydata-sphinx-theme ; extra == 'docs'
Requires-Dist: sphinxcontrib-bibtex ; extra == 'docs'
